fsos/__init__.py
fsos/bucket_manager.py
fsos/bucket_manager_test.py
fsos/deco.py
fsos/deco_test.py
fsos/fs_manager.py
fsos/fs_manager_test.py
fsos/os_manager.py
fsos/utils.py
fsos/utils_test.py
fsos-0.0.1.dist-info/METADATA
fsos-0.0.1.dist-info/WHEEL
fsos-0.0.1.dist-info/top_level.txt
fsos-0.0.1.dist-info/RECORD
