Metadata-Version: 2.1
Name: fsos
Version: 0.0.1
Summary: minio like python Local File System based Object Storage (FSOS)
Home-page: https://github.com/davinnovation/fsos
License: UNKNOWN
Platform: UNKNOWN
Classifier: Programming Language :: Python :: 3
Classifier: License :: OSI Approved :: MIT License
Classifier: Operating System :: OS Independent
Requires-Python: >=3.6
